uv_workon/__init__.py
uv_workon/__main__.py
uv_workon/_click.py
uv_workon/_compat.py
uv_workon/_logger.py
uv_workon/_typing.py
uv_workon/_typing_compat.py
uv_workon/cli.py
uv_workon/core.py
uv_workon/kernels.py
uv_workon/py.typed
uv_workon/scripts/ipykernel_install_script.py
uv_workon/utils.py
uv_workon/validate.py
uv_workon-0.7.2.dist-info/licenses/LICENSE
uv_workon-0.7.2.dist-info/WHEEL
uv_workon-0.7.2.dist-info/entry_points.txt
uv_workon-0.7.2.dist-info/METADATA
uv_workon-0.7.2.dist-info/RECORD
