Metadata-Version: 2.4
Name: uv-workon
Version: 0.7.2
Summary: Tools to activate and run virtual environments from central location
Keywords: uv-workon
Author: William P. Krekelberg
Author-email: William P. Krekelberg <wpk@nist.gov>
License-Expression: NIST-PD
License-File: LICENSE
Classifier: Development Status :: 2 - Pre-Alpha
Classifier: Intended Audience :: Science/Research
Classifier: Operating System :: OS Independent
Classifier: Programming Language :: Python
Classifier: Programming Language :: Python :: 3 :: Only
Classifier: Programming Language :: Python :: 3.10
Classifier: Programming Language :: Python :: 3.11
Classifier: Programming Language :: Python :: 3.12
Classifier: Programming Language :: Python :: 3.13
Classifier: Programming Language :: Python :: 3.14
Classifier: Topic :: Scientific/Engineering
Requires-Dist: attrs>=25.3.0
Requires-Dist: simple-term-menu>=1.6.6
Requires-Dist: typer>=0.15.2
Requires-Dist: typing-extensions>=4.12.2 ; python_full_version < '3.11'
Requires-Dist: uv-workon[jupyter] ; extra == 'all'
Requires-Dist: jupyter-client>=8.6.3 ; extra == 'jupyter'
Requires-Python: >=3.10
Project-URL: Documentation, https://pages.nist.gov/uv-workon/
Project-URL: Homepage, https://github.com/usnistgov/uv-workon
Provides-Extra: all
Provides-Extra: jupyter
